hxq_login_mcp/__init__.py
hxq_login_mcp/__main__.py
hxq_login_mcp/server.py
hxq_login_mcp-1.0.1.dist-info/METADATA
hxq_login_mcp-1.0.1.dist-info/WHEEL
hxq_login_mcp-1.0.1.dist-info/entry_points.txt
hxq_login_mcp-1.0.1.dist-info/RECORD
