Metadata-Version: 2.4
Name: hxq-login-mcp
Version: 1.0.1
Summary: MCP server for HXQ (盒小圈) login API
Project-URL: Homepage, https://github.com/yourusername/hxq-login-mcp
Project-URL: Repository, https://github.com/yourusername/hxq-login-mcp
Author-email: Your Name <your.email@example.com>
License: MIT
Classifier: Development Status :: 4 - Beta
Classifier: Intended Audience :: Developers
Classifier: Programming Language :: Python :: 3
Classifier: Programming Language :: Python :: 3.8
Classifier: Programming Language :: Python :: 3.9
Classifier: Programming Language :: Python :: 3.10
Classifier: Programming Language :: Python :: 3.11
Classifier: Topic :: Software Development :: Libraries :: Python Modules
Requires-Dist: httpx>=0.25.0
Requires-Dist: mcp>=1.0.0
Requires-Dist: pydantic>=2.0.0
